{
    "boxShadow": "none",
    "widgetName": "IconButton9",
    "onClick": "{{CurrentTask.deleteTimelog(currentItem.id)}}",
    "buttonColor": "{{appsmith.theme.colors.primaryColor}}",
    "dynamicPropertyPathList": [{"key": "onClick"}],
    "displayName": "Icon button",
    "iconSVG": "/static/media/icon.b08054586989b185a0801e9a34f8ad49.svg",
    "searchTags": [
        "click",
        "submit"
    ],
    "topRow": 4.8,
    "bottomRow": 8.8,
    "parentRowSpace": 10,
    "type": "ICON_BUTTON_WIDGET",
    "hideCard": false,
    "animateLoading": true,
    "parentColumnSpace": 16.671875,
    "dynamicTriggerPathList": [{"key": "onClick"}],
    "leftColumn": 0,
    "dynamicBindingPathList": [
        {"key": "buttonColor"},
        {"key": "borderRadius"}
    ],
    "isDisabled": false,
    "key": "o9lome8kc3",
    "isDeprecated": false,
    "rightColumn": 7,
    "iconName": "delete",
    "dynamicHeight": "AUTO_HEIGHT",
    "widgetId": "zaxzyf8l5p",
    "minWidth": 50,
    "isVisible": true,
    "version": 1,
    "parentId": "x8176fyi7c",
    "tags": ["Buttons"],
    "renderMode": "CANVAS",
    "isLoading": false,
    "borderRadius": "{{appsmith.theme.borderRadius.appBorderRadius}}",
    "buttonVariant": "TERTIARY"
}